[
  {
    "id": "avnet",
    "name": "avnet",
    "vendor": "Xilinx",
    "model": "AVNET",
    "source": "linux_dt",
    "aliases": [
      "avnet (AVNET)"
    ],
    "completeness": 0.1205,
    "sources": {},
    "updated": "2026-06-21",
    "provenance": {
      "name": "legacy_v2",
      "vendor": "legacy_v2",
      "model": "legacy_v2",
      "source": "legacy_v2",
      "aliases": "legacy_v2"
    }
  },
  {
    "id": "versal",
    "name": "versal",
    "vendor": "Xilinx",
    "model": "VERSAL",
    "source": "linux_dt",
    "aliases": [
      "versal (VERSAL)"
    ],
    "completeness": 0.1687,
    "sources": {},
    "updated": "2026-06-21",
    "cores": 16,
    "architecture": "ARMv8.2-A",
    "provenance": {
      "name": "legacy_v2",
      "vendor": "legacy_v2",
      "model": "legacy_v2",
      "source": "legacy_v2",
      "aliases": "legacy_v2",
      "cores": "legacy_v2",
      "architecture": "legacy_v2"
    }
  },
  {
    "id": "zynqmp",
    "name": "zynqmp",
    "vendor": "Xilinx",
    "model": "ZYNQMP",
    "source": "linux_dt",
    "cores": 4,
    "architecture": "ARMv8-A",
    "completeness": 0.1687,
    "sources": {},
    "updated": "2026-06-21",
    "aliases": [
      "zynqmp (ZYNQMP)"
    ],
    "provenance": {
      "name": "legacy_v2",
      "vendor": "legacy_v2",
      "model": "legacy_v2",
      "source": "legacy_v2",
      "cores": "legacy_v2",
      "architecture": "legacy_v2",
      "aliases": "legacy_v2"
    }
  },
  {
    "id": "zynqmpi",
    "name": "zynqmpi",
    "vendor": "Xilinx",
    "model": "ZYNQMPI",
    "source": "linux_dt",
    "aliases": [
      "zynqmpi (ZYNQMPI)"
    ],
    "completeness": 0.1687,
    "sources": {},
    "updated": "2026-06-21",
    "cores": 4,
    "architecture": "ARMv8-A",
    "provenance": {
      "name": "legacy_v2",
      "vendor": "legacy_v2",
      "model": "legacy_v2",
      "source": "legacy_v2",
      "aliases": "legacy_v2",
      "cores": "legacy_v2",
      "architecture": "legacy_v2"
    }
  }
]
